redditsweeper/__init__.py
redditsweeper/__version__.py
redditsweeper/app.py
redditsweeper/exceptions.py
redditsweeper/sweeper.py
redditsweeper-1.0.1.dist-info/entry_points.txt
redditsweeper-1.0.1.dist-info/LICENSE
redditsweeper-1.0.1.dist-info/WHEEL
redditsweeper-1.0.1.dist-info/METADATA
redditsweeper-1.0.1.dist-info/RECORD
