Metadata-Version: 2.1
Name: redditsweeper
Version: 1.0.1
Summary: Tool for automated removal of old reddit comments.
Home-page: https://www.github.com/scott-hand/redditsweeper
License: MIT
Author: Scott Hand
Requires-Python: >=2.7, !=3.0.*, !=3.1.*, !=3.2.*, !=3.3.*, !=3.4.*, !=3.5.*
Classifier: License :: OSI Approved :: MIT License
Classifier: Programming Language :: Python :: 2
Classifier: Programming Language :: Python :: 2.7
Classifier: Programming Language :: Python :: 3
Classifier: Programming Language :: Python :: 3.6
Classifier: Programming Language :: Python :: 3.7
Requires-Dist: ConfigArgParse (>=0.13.0,<0.14.0)
Requires-Dist: colorama (>=0.4.0,<0.5.0)
Requires-Dist: praw (>=6.0,<7.0)
Project-URL: Repository, https://www.github.com/scott-hand/redditsweeper
